kris_poetry/__init__.py
kris_poetry-0.1.0.dist-info/METADATA
kris_poetry-0.1.0.dist-info/WHEEL
kris_poetry-0.1.0.dist-info/RECORD
